py_msgpack_rpc/__init__.py
py_msgpack_rpc/_client/__init__.py
py_msgpack_rpc/_client/_async_client.py
py_msgpack_rpc/_client/py.typed
py_msgpack_rpc/_exceptions.py
py_msgpack_rpc/_messages.py
py_msgpack_rpc/_server/__init__.py
py_msgpack_rpc/_server/_async_server.py
py_msgpack_rpc/_server/_method_executor.py
py_msgpack_rpc/_server/py.typed
py_msgpack_rpc/py.typed
py_msgpack_rpc-0.1.0a2.dist-info/METADATA
py_msgpack_rpc-0.1.0a2.dist-info/WHEEL
py_msgpack_rpc-0.1.0a2.dist-info/RECORD
