Metadata-Version: 2.1
Name: py-msgpack-rpc
Version: 0.1.0a2
Summary: An RPC library implementing MessagePack RPC in Python.
Home-page: https://gitlab.com/MusicScience37Projects/utility-libraries/py-msgpack-rpc
License: MIT
Author: Kenta Kabashima
Author-email: kenta_program37@hotmail.co.jp
Requires-Python: >=3.10,<3.12
Classifier: Development Status :: 2 - Pre-Alpha
Classifier: Framework :: AsyncIO
Classifier: Intended Audience :: Developers
Classifier: License :: OSI Approved :: MIT License
Classifier: Operating System :: OS Independent
Classifier: Programming Language :: Python :: 3
Classifier: Programming Language :: Python :: 3.10
Classifier: Programming Language :: Python :: 3.11
Classifier: Topic :: System :: Networking
Classifier: Typing :: Typed
Requires-Dist: msgpack (>=1.0.5,<2.0.0)
Project-URL: Repository, https://gitlab.com/MusicScience37Projects/utility-libraries/py-msgpack-rpc.git
